webtest_asgi.py
webtest_asgi-2.0.0.dist-info/licenses/LICENSE
webtest_asgi-2.0.0.dist-info/WHEEL
webtest_asgi-2.0.0.dist-info/METADATA
webtest_asgi-2.0.0.dist-info/RECORD
