Metadata-Version: 2.4
Name: webtest-asgi
Version: 2.0.0
Summary: webtest-asgi provides integration of WebTest with ASGI applications
Maintainer-email: Steven Loria <sloria1@gmail.com>
Requires-Python: >=3.9
Classifier: Intended Audience :: Developers
Classifier: License :: OSI Approved :: MIT License
Classifier: Natural Language :: English
Classifier: Programming Language :: Python :: 3
Classifier: Programming Language :: Python :: 3.9
Classifier: Programming Language :: Python :: 3.10
Classifier: Programming Language :: Python :: 3.11
Classifier: Programming Language :: Python :: 3.12
Classifier: Programming Language :: Python :: 3.13
Classifier: Topic :: System :: Shells
License-File: LICENSE
Requires-Dist: webtest
Requires-Dist: starlette>=0.38.0
Requires-Dist: httpx>=0.27.1
Requires-Dist: python-multipart
Requires-Dist: webtest-asgi[tests] ; extra == "dev"
Requires-Dist: tox ; extra == "dev"
Requires-Dist: pre-commit>=3.5,<5.0 ; extra == "dev"
Requires-Dist: pytest ; extra == "tests"
Project-URL: Issues, https://github.com/sloria/webtest-asgi/issues
Project-URL: Source, https://github.com/sloria/webtest-asgi
Provides-Extra: dev
Provides-Extra: tests
